selfies_tokenizer/__init__.py
selfies_tokenizer/tokenizer.py
selfies_tokenizer/utils.py
selfies_tokenizer-0.1.4.dist-info/licenses/LICENSE
selfies_tokenizer-0.1.4.dist-info/METADATA
selfies_tokenizer-0.1.4.dist-info/WHEEL
selfies_tokenizer-0.1.4.dist-info/top_level.txt
selfies_tokenizer-0.1.4.dist-info/RECORD
