Metadata-Version: 2.4
Name: selfies-tokenizer
Version: 0.1.4
Summary: Super fast tokenizer for SELFIES molecular representations with ML-ready batch processing
Author-email: Rudra Sondhi <rudra.sondhi2@gmail.com>
License-Expression: MIT
Project-URL: Homepage, https://github.com/rudra-sondhi/selfies-tokenizer
Project-URL: Documentation, https://github.com/rudra-sondhi/selfies-tokenizer#readme
Project-URL: Repository, https://github.com/rudra-sondhi/selfies-tokenizer
Keywords: selfies,tokenizer,chemistry,molecular,machine-learning,cheminformatics
Classifier: Development Status :: 4 - Beta
Classifier: Intended Audience :: Science/Research
Classifier: Intended Audience :: Developers
Classifier: Programming Language :: Python :: 3
Classifier: Programming Language :: Python :: 3.7
Classifier: Programming Language :: Python :: 3.8
Classifier: Programming Language :: Python :: 3.9
Classifier: Programming Language :: Python :: 3.10
Classifier: Programming Language :: Python :: 3.11
Classifier: Topic :: Scientific/Engineering :: Chemistry
Classifier: Topic :: Scientific/Engineering :: Artificial Intelligence
Requires-Python: >=3.7
License-File: LICENSE
Requires-Dist: numpy>=1.19.0
Provides-Extra: dev
Requires-Dist: pytest>=7.0; extra == "dev"
Requires-Dist: tqdm>=4.62.0; extra == "dev"
Requires-Dist: selfies>=2.0.0; extra == "dev"
Provides-Extra: all
Requires-Dist: tqdm>=4.62.0; extra == "all"
Requires-Dist: selfies>=2.0.0; extra == "all"
Dynamic: license-file
